{"id":380,"x":900,"y":140,"default":"grass","layers":[[]],"decor":[[0,11,"t4"],[0,17,"t3"],[2,5,"t3"],[4,2,"t4"],[4,14,"t3"],[5,7,"t4"],[6,12,"t4"],[7,0,"t3"],[7,19,"t3"],[8,8,"t4"],[8,14,"t3"],[9,6,"t3"],[10,12,"t3"],[11,1,"t3"],[11,15,"t3"],[12,6,"t4"],[12,10,"t4"],[15,5,"t3"],[15,14,"t4"],[17,9,"t3"],[17,11,"t3"],[18,15,"t3"],[18,18,"t3"],[19,13,"t3"],[22,9,"t4"],[22,13,"t4"],[22,15,"t4"],[22,18,"t3"],[23,11,"t4"],[25,14,"t3"],[25,17,"t4"],[26,2,"t4"],[26,6,"t4"],[26,8,"t4"],[26,11,"t4"],[28,0,"t3"],[28,14,"t3"],[28,16,"t4"],[28,18,"t3"],[29,2,"t4"],[29,9,"t4"],[29,12,"t4"]]}