{"id":776,"x":780,"y":300,"default":"grass","layers":[[[7,4,"c"],[7,5,"c"],[8,3,"c"],[8,4,"c"],[8,5,"c"],[9,3,"c"],[9,5,"c"],[10,3,"c"],[10,4,"c"],[10,5,"c"]]],"decor":[[10,1,"t4"],[5,2,"t4"],[29,2,"t4"],[1,2,"t4"],[16,1,"t4"],[26,0,"t4"],[23,8,"t4"],[21,6,"td"],[27,10,"t4"],[27,5,"t4"],[16,5,"t4"],[19,4,"t4"],[28,7,"t4"],[20,0,"t4"],[17,9,"t4"],[16,3,"t4"],[0,14,"t4"],[0,17,"t4"],[26,19,"t4"],[21,16,"t4"],[18,16,"t4"],[24,15,"t4"],[16,13,"t4"],[21,14,"td"],[7,17,"t4"],[11,16,"t4"],[10,18,"t4"]]}