{"id":126,"x":780,"y":40,"default":"grass","layers":[[[4,19,"c"],[5,19,"c"],[6,19,"c"],[7,19,"c"],[28,19,"c"],[29,16,"c"],[29,17,"c"],[29,19,"c"]]],"decor":[[3,0,"t3"],[15,0,"t3"],[6,1,"t3"],[20,1,"t3"],[11,1,"t3"],[15,2,"t3"],[24,2,"t3"],[29,0,"t3"],[12,3,"t3"],[9,3,"t3"],[5,3,"t3"],[19,3,"t3"],[2,2,"t3"],[8,5,"t3"],[28,5,"t3"],[20,5,"t3"],[24,5,"t3"],[4,6,"t3"],[27,3,"t3"],[17,5,"td"],[1,4,"t3"],[10,7,"t3"],[17,7,"t3"],[2,8,"t3"],[25,8,"t3"],[14,6,"t3"],[7,8,"t3"],[20,9,"t3"],[17,9,"t3"],[10,9,"t3"],[4,10,"t3"],[14,9,"t3"],[28,7,"t3"],[10,12,"t3"],[15,12,"t3"],[1,12,"t3"],[7,11,"t3"],[11,5,"t3"],[18,12,"t3"],[6,13,"t3"],[23,11,"t3"],[1,15,"t3"],[17,15,"t3"],[20,7,"t3"],[8,15,"t3"],[20,15,"t3"],[13,15,"t3"],[9,17,"t3"],[0,17,"t3"],[16,17,"t3"],[5,17,"t3"],[8,19,"t3"],[12,18,"t3"]]}