{"id":1372,"x":660,"y":540,"default":"grass","layers":[[[0,0,"c"],[0,4,"c"],[0,5,"c"],[0,6,"wt"],[0,7,"w"],[0,8,"w"],[0,9,"w"],[0,10,"w"],[0,11,"w"],[0,12,"wb"],[0,14,"c"],[0,15,"c"],[0,18,"c"],[0,19,"c"],[1,0,"wbbl"],[1,1,"c"],[1,2,"c"],[1,5,"c"],[1,6,"wt"],[1,7,"w"],[1,8,"w"],[1,9,"w"],[1,10,"w"],[1,11,"wctl"],[1,12,"wbbr"],[1,18,"c"],[1,19,"c"],[2,0,"wb"],[2,1,"c"],[2,2,"c"],[2,5,"c"],[2,6,"wt"],[2,7,"w"],[2,8,"w"],[2,9,"w"],[2,10,"w"],[2,11,"wb"],[2,16,"wbtl"],[2,17,"wl"],[2,18,"wl"],[2,19,"wl"],[3,0,"wbbr"],[3,1,"c"],[3,2,"c"],[3,5,"c"],[3,6,"wt"],[3,7,"w"],[3,8,"w"],[3,9,"w"],[3,10,"w"],[3,11,"wctr"],[3,12,"wbbl"],[3,16,"wt"],[3,17,"w"],[3,18,"w"],[3,19,"w"],[4,0,"c"],[4,2,"c"],[4,5,"c"],[4,6,"wt"],[4,7,"w"],[4,8,"w"],[4,9,"w"],[4,10,"w"],[4,11,"w"],[4,12,"wb"],[4,14,"c"],[4,15,"c"],[4,16,"wt"],[4,17,"w"],[4,18,"w"],[4,19,"w"],[5,0,"c"],[5,1,"c"],[5,2,"c"],[5,5,"c"],[5,6,"wbtr"],[5,7,"wr"],[5,8,"wr"],[5,9,"wcbl"],[5,10,"w"],[5,11,"w"],[5,12,"wctr"],[5,13,"wl"],[5,14,"wl"],[5,15,"wl"],[5,16,"wcbr"],[5,17,"w"],[5,18,"w"],[5,19,"w"],[6,1,"c"],[6,2,"c"],[6,3,"c"],[6,4,"c"],[6,5,"c"],[6,7,"c"],[6,8,"c"],[6,9,"wbtr"],[6,10,"wcbl"],[6,11,"w"],[6,12,"w"],[6,13,"w"],[6,14,"w"],[6,15,"w"],[6,16,"w"],[6,17,"w"],[6,18,"w"],[6,19,"w"],[7,10,"wt"],[7,11,"w"],[7,12,"w"],[7,13,"w"],[7,14,"w"],[7,15,"w"],[7,16,"w"],[7,17,"w"],[7,18,"w"],[7,19,"w"],[8,9,"wbtl"],[8,10,"wcbr"],[8,11,"w"],[8,12,"w"],[8,13,"w"],[8,14,"w"],[8,15,"w"],[8,16,"w"],[8,17,"w"],[8,18,"w"],[8,19,"w"],[9,9,"wt"],[9,10,"w"],[9,11,"w"],[9,12,"w"],[9,13,"w"],[9,14,"w"],[9,15,"w"],[9,16,"w"],[9,17,"w"],[9,18,"w"],[9,19,"w"],[10,8,"wbtl"],[10,9,"wcbr"],[10,10,"w"],[10,11,"w"],[10,12,"w"],[10,13,"w"],[10,14,"w"],[10,15,"w"],[10,16,"w"],[10,17,"w"],[10,18,"w"],[10,19,"w"],[11,6,"wbtl"],[11,7,"wl"],[11,8,"wcbr"],[11,9,"w"],[11,10,"w"],[11,11,"w"],[11,12,"w"],[11,13,"w"],[11,14,"w"],[11,15,"w"],[11,16,"w"],[11,17,"w"],[11,18,"w"],[11,19,"w"],[12,6,"wt"],[12,7,"w"],[12,8,"w"],[12,9,"w"],[12,10,"w"],[12,11,"w"],[12,12,"w"],[12,13,"w"],[12,14,"w"],[12,15,"w"],[12,16,"w"],[12,17,"w"],[12,18,"wctl"],[12,19,"wr"],[13,3,"c"],[13,4,"c"],[13,6,"wbtr"],[13,7,"wcbl"],[13,8,"w"],[13,9,"w"],[13,10,"w"],[13,11,"w"],[13,12,"w"],[13,13,"w"],[13,14,"w"],[13,15,"w"],[13,16,"w"],[13,17,"w"],[13,18,"wb"],[14,3,"wbtl"],[14,4,"wl"],[14,5,"wl"],[14,6,"wl"],[14,7,"wcbr"],[14,8,"w"],[14,9,"w"],[14,10,"w"],[14,11,"w"],[14,12,"w"],[14,13,"w"],[14,14,"w"],[14,15,"w"],[14,16,"w"],[14,17,"w"],[14,18,"wb"],[15,3,"wt"],[15,4,"w"],[15,5,"w"],[15,6,"w"],[15,7,"w"],[15,8,"w"],[15,9,"w"],[15,10,"w"],[15,11,"w"],[15,12,"w"],[15,13,"w"],[15,14,"w"],[15,15,"w"],[15,16,"w"],[15,17,"w"],[15,18,"wctr"],[15,19,"wbbl"],[16,2,"wbtl"],[16,3,"wcbr"],[16,4,"w"],[16,5,"w"],[16,6,"w"],[16,7,"w"],[16,8,"wctl"],[16,9,"wr"],[16,10,"wr"],[16,11,"wr"],[16,12,"wr"],[16,13,"wr"],[16,14,"wcbl"],[16,15,"w"],[16,16,"w"],[16,17,"w"],[16,18,"w"],[16,19,"wb"],[17,2,"wt"],[17,3,"w"],[17,4,"w"],[17,5,"wctl"],[17,6,"wr"],[17,7,"wr"],[17,8,"c"],[17,9,"c"],[17,10,"c"],[17,12,"c"],[17,13,"c"],[17,14,"wt"],[17,15,"w"],[17,16,"w"],[17,17,"w"],[17,18,"w"],[17,19,"wb"],[18,2,"wbtr"],[18,3,"wcbl"],[18,4,"w"],[18,5,"wb"],[18,12,"wbtl"],[18,13,"wl"],[18,14,"wcbr"],[18,15,"w"],[18,16,"w"],[18,17,"w"],[18,18,"w"],[18,19,"wb"],[19,3,"wt"],[19,4,"w"],[19,5,"wb"],[19,12,"wt"],[19,13,"w"],[19,14,"w"],[19,15,"w"],[19,16,"w"],[19,17,"w"],[19,18,"w"],[19,19,"wb"],[20,2,"wbtl"],[20,3,"wcbr"],[20,4,"w"],[20,5,"wb"],[20,12,"wt"],[20,13,"w"],[20,14,"w"],[20,15,"w"],[20,16,"w"],[20,17,"w"],[20,18,"w"],[20,19,"wctr"],[21,0,"wbtl"],[21,1,"wl"],[21,2,"wcbr"],[21,3,"w"],[21,4,"w"],[21,5,"wctr"],[21,6,"wbbl"],[21,10,"wbtl"],[21,11,"wl"],[21,12,"wcbr"],[21,13,"w"],[21,14,"w"],[21,15,"w"],[21,16,"w"],[21,17,"w"],[21,18,"w"],[21,19,"w"],[22,0,"wt"],[22,1,"w"],[22,2,"w"],[22,3,"w"],[22,4,"w"],[22,5,"w"],[22,6,"wb"],[22,9,"wbtl"],[22,10,"wcbr"],[22,11,"w"],[22,12,"w"],[22,13,"w"],[22,14,"wctl"],[22,15,"wr"],[22,16,"wr"],[22,17,"wr"],[22,18,"wcbl"],[22,19,"w"],[23,0,"wt"],[23,1,"w"],[23,2,"w"],[23,3,"w"],[23,4,"w"],[23,5,"wctl"],[23,6,"wbbr"],[23,8,"wbtl"],[23,9,"wcbr"],[23,10,"w"],[23,11,"w"],[23,12,"w"],[23,13,"wctl"],[23,14,"wbbr"],[23,16,"c"],[23,17,"c"],[23,18,"wt"],[23,19,"w"],[24,0,"wbtr"],[24,1,"wcbl"],[24,2,"w"],[24,3,"w"],[24,4,"w"],[24,5,"wb"],[24,8,"wt"],[24,9,"w"],[24,10,"w"],[24,11,"w"],[24,12,"w"],[24,13,"wb"],[24,16,"wbtl"],[24,17,"wl"],[24,18,"wcbr"],[24,19,"w"],[25,1,"wbtr"],[25,2,"wr"],[25,3,"wr"],[25,4,"wr"],[25,5,"wbbr"],[25,8,"wbtr"],[25,9,"wcbl"],[25,10,"w"],[25,11,"w"],[25,12,"wctl"],[25,13,"wbbr"],[25,16,"wt"],[25,17,"w"],[25,18,"w"],[25,19,"w"],[26,8,"wbtl"],[26,9,"wcbr"],[26,10,"w"],[26,11,"wctl"],[26,12,"wbbr"],[26,16,"wbtr"],[26,17,"wr"],[26,18,"wr"],[26,19,"wr"],[27,8,"wt"],[27,9,"w"],[27,10,"w"],[27,11,"wb"],[28,8,"wt"],[28,9,"w"],[28,10,"wctl"],[28,11,"wbbr"],[29,8,"wt"],[29,9,"w"],[29,10,"wb"]]],"decor":[[26,3,"t1"],[27,6,"t1"],[29,3,"t1"]]}